svkcore/__init__.py
svkcore/annotation/__init__.py
svkcore/annotation/pascal.py
svkcore/assets/DFPKingGothicGB-Light-2.ttf
svkcore/common/__init__.py
svkcore/common/common.py
svkcore/common/fileio.py
svkcore/common/np_ops.py
svkcore/shapes/__init__.py
svkcore/shapes/shapes.py
svkcore/visualize/__init__.py
svkcore/visualize/visualize.py
svkcore-0.0.9.dist-info/METADATA
svkcore-0.0.9.dist-info/RECORD
svkcore-0.0.9.dist-info/WHEEL
svkcore-0.0.9.dist-info/top_level.txt
