Metadata-Version: 2.1
Name: svkcore
Version: 0.0.9
Summary: A simple deep computer vision toolkit
Home-page: https://github.com/ZhaoJianghua/simple-vision-kit.git
Author: zjh
Author-email: zhaojianghua1990@qq.com
License: UNKNOWN
Platform: UNKNOWN
Classifier: Programming Language :: Python :: 3
Classifier: License :: OSI Approved :: MIT License
Classifier: Operating System :: OS Independent
Requires-Python: >=3.6
Requires-Dist: pillow
Requires-Dist: opencv-python
Requires-Dist: numpy
Requires-Dist: lxml
